odoo/addons/ddmrp_cron_actions_as_job/README.rst
odoo/addons/ddmrp_cron_actions_as_job/__init__.py
odoo/addons/ddmrp_cron_actions_as_job/__manifest__.py
odoo/addons/ddmrp_cron_actions_as_job/data/queue_job_channel_data.xml
odoo/addons/ddmrp_cron_actions_as_job/data/queue_job_function_data.xml
odoo/addons/ddmrp_cron_actions_as_job/i18n/ddmrp_cron_actions_as_job.pot
odoo/addons/ddmrp_cron_actions_as_job/models/__init__.py
odoo/addons/ddmrp_cron_actions_as_job/models/stock_buffer.py
odoo/addons/ddmrp_cron_actions_as_job/models/stock_move.py
odoo/addons/ddmrp_cron_actions_as_job/readme/CONTRIBUTORS.rst
odoo/addons/ddmrp_cron_actions_as_job/readme/DESCRIPTION.rst
odoo/addons/ddmrp_cron_actions_as_job/static/description/icon.png
odoo/addons/ddmrp_cron_actions_as_job/static/description/index.html
odoo/addons/ddmrp_cron_actions_as_job/tests/__init__.py
odoo/addons/ddmrp_cron_actions_as_job/tests/test_cron_actions_as_job.py
odoo13_addon_ddmrp_cron_actions_as_job-13.0.1.2.0.dist-info/METADATA
odoo13_addon_ddmrp_cron_actions_as_job-13.0.1.2.0.dist-info/WHEEL
odoo13_addon_ddmrp_cron_actions_as_job-13.0.1.2.0.dist-info/top_level.txt
odoo13_addon_ddmrp_cron_actions_as_job-13.0.1.2.0.dist-info/RECORD
